anyblok_attachment/__init__.py
anyblok_attachment/config.py
anyblok_attachment/conftest.py
anyblok_attachment/release.py
anyblok_attachment/bloks/__init__.py
anyblok_attachment/bloks/attachment/CODE.rst
anyblok_attachment/bloks/attachment/README.rst
anyblok_attachment/bloks/attachment/__init__.py
anyblok_attachment/bloks/attachment/attachment.py
anyblok_attachment/bloks/attachment/document.py
anyblok_attachment/bloks/attachment/exceptions.py
anyblok_attachment/bloks/attachment/mixin.py
anyblok_attachment/bloks/attachment/tests/__init__.py
anyblok_attachment/bloks/attachment/tests/test_historized.py
anyblok_attachment/bloks/attachment/tests/test_latest.py
anyblok_attachment/bloks/format/CODE.rst
anyblok_attachment/bloks/format/README.rst
anyblok_attachment/bloks/format/__init__.py
anyblok_attachment/bloks/format/template.py
anyblok_attachment/bloks/format/tests/__init__.py
anyblok_attachment/bloks/format/tests/test_format.py
anyblok_attachment/bloks/postgres/__init__.py
anyblok_attachment/bloks/postgres/document.py
anyblok_attachment/bloks/report/CODE.rst
anyblok_attachment/bloks/report/README.rst
anyblok_attachment/bloks/report/__init__.py
anyblok_attachment/bloks/report/common.py
anyblok_attachment/bloks/report/document.py
anyblok_attachment/bloks/report/exceptions.py
anyblok_attachment/bloks/report/parser.py
anyblok_attachment/bloks/report/template.py
anyblok_attachment/bloks/report/tests/__init__.py
anyblok_attachment/bloks/report/tests/test_common.py
anyblok_attachment/bloks/report/tests/test_parser.py
anyblok_attachment/bloks/report/tests/test_template.py
anyblok_attachment/bloks/wkhtml2pdf/CODE.rst
anyblok_attachment/bloks/wkhtml2pdf/README.rst
anyblok_attachment/bloks/wkhtml2pdf/__init__.py
anyblok_attachment/bloks/wkhtml2pdf/exceptions.py
anyblok_attachment/bloks/wkhtml2pdf/mixin.py
anyblok_attachment/bloks/wkhtml2pdf/model.py
anyblok_attachment/bloks/wkhtml2pdf/tests/__init__.py
anyblok_attachment/bloks/wkhtml2pdf/tests/test_page.py
anyblok_attachment-2.2.0.dist-info/LICENSE.rst
anyblok_attachment-2.2.0.dist-info/METADATA
anyblok_attachment-2.2.0.dist-info/WHEEL
anyblok_attachment-2.2.0.dist-info/entry_points.txt
anyblok_attachment-2.2.0.dist-info/top_level.txt
anyblok_attachment-2.2.0.dist-info/RECORD
