Metadata-Version: 2.1
Name: anyblok-attachment
Version: 2.2.0
Summary: Versionned attachment for AnyBlok
Home-page: http://docs.anyblok-attachment.anyblok.org/2.2.0
Author: jssuzanne
Author-email: jssuzanne@anybox.fr
License: UNKNOWN
Keywords: attachment
Platform: UNKNOWN
Classifier: Development Status :: 5 - Production/Stable
Classifier: Intended Audience :: Developers
Classifier: Natural Language :: English
Classifier: Programming Language :: Python :: 3
Classifier: Programming Language :: Python :: 3.6
Classifier: Programming Language :: Python :: 3.7
Classifier: Programming Language :: Python :: 3.8
Classifier: Programming Language :: Python :: 3.9
Classifier: Programming Language :: Python :: 3.10
Requires-Dist: anyblok (>=1.2.0)
Requires-Dist: anyblok-mixins
